PySide6FlexUI/__init__.py
PySide6FlexUI/components/__init__.py
PySide6FlexUI/components/data_entry/__init__.py
PySide6FlexUI/components/data_entry/auto_complete.py
PySide6FlexUI/components/data_entry/cascader.py
PySide6FlexUI/components/data_entry/checkbox.py
PySide6FlexUI/components/data_entry/color_picker.py
PySide6FlexUI/components/data_entry/date_picker.py
PySide6FlexUI/components/data_entry/form.py
PySide6FlexUI/components/data_entry/input.py
PySide6FlexUI/components/data_entry/input_number.py
PySide6FlexUI/components/data_entry/mentions.py
PySide6FlexUI/components/data_entry/radio.py
PySide6FlexUI/components/data_entry/rate.py
PySide6FlexUI/components/data_entry/select.py
PySide6FlexUI/components/data_entry/slider.py
PySide6FlexUI/components/data_entry/switch.py
PySide6FlexUI/components/data_entry/time_picker.py
PySide6FlexUI/components/data_entry/transfer.py
PySide6FlexUI/components/data_entry/tree_select.py
PySide6FlexUI/components/data_entry/upload.py
PySide6FlexUI/components/date_display/__init__.py
PySide6FlexUI/components/date_display/avatar.py
PySide6FlexUI/components/date_display/badge.py
PySide6FlexUI/components/date_display/calandar.py
PySide6FlexUI/components/date_display/card.py
PySide6FlexUI/components/date_display/carousel.py
PySide6FlexUI/components/date_display/descriptions.py
PySide6FlexUI/components/date_display/empty.py
PySide6FlexUI/components/date_display/image.py
PySide6FlexUI/components/date_display/list.py
PySide6FlexUI/components/date_display/popover.py
PySide6FlexUI/components/date_display/qrcode.py
PySide6FlexUI/components/date_display/segmented.py
PySide6FlexUI/components/date_display/statistic.py
PySide6FlexUI/components/date_display/table.py
PySide6FlexUI/components/date_display/tag.py
PySide6FlexUI/components/date_display/timeline.py
PySide6FlexUI/components/date_display/tooltip.py
PySide6FlexUI/components/date_display/tour.py
PySide6FlexUI/components/date_display/tree.py
PySide6FlexUI/components/date_time/__init__.py
pyside6_flex_ui-0.1.1.dist-info/METADATA
pyside6_flex_ui-0.1.1.dist-info/WHEEL
pyside6_flex_ui-0.1.1.dist-info/top_level.txt
pyside6_flex_ui-0.1.1.dist-info/RECORD
