Metadata-Version: 2.4
Name: PySide6-Flex-UI
Version: 0.1.1
Summary: Add your description here
Requires-Python: >=3.10
Requires-Dist: commons-lang>=0.2.11
Requires-Dist: pyside6>=6.9.0
